{
  "issues": [],
  "warnings": [
    "Node 'function:Engine.UnitTests/MixinTests.cs:ToDynamicMember_L872' has no edges (orphan)",
    "Node 'function:Engine.UnitTests/MixinTests.cs:ToDynamicMember_L916' has no edges (orphan)",
    "Node 'file:Engine.UnitTests/PerformanceTests.cs' has no edges (orphan)",
    "Node 'file:Engine.UnitTests/Properties/AssemblyInfo.cs' has no edges (orphan)",
    "Node 'function:Engine.UnitTests/MemberDataProviderTests.cs:GetTypeData_L411' has no edges (orphan)",
    "Node 'function:Engine.UnitTests/ProcessStepTest.cs:Execute_L16' has no edges (orphan)",
    "Node 'file:Engine.UnitTests/TestPlanEmptyStringProp.cs' has no edges (orphan)",
    "Node 'file:Engine.UnitTests/TestPlanTestFixture1.cs' has no edges (orphan)",
    "Node 'file:Engine.UnitTests/TestPlanTestFixture2.cs' has no edges (orphan)",
    "Node 'file:Engine.UnitTests/TestPlanTestFixture3.cs' has no edges (orphan)",
    "Node 'file:Engine.UnitTests/TestPlanTimespan.cs' has no edges (orphan)",
    "Node 'file:Engine.UnitTests/TestStepNameFormattingTests.cs' has no edges (orphan)",
    "Node 'file:Engine.UnitTests/TestTestPlans/tap70_sweep_loop.TapPlan' has no edges (orphan)",
    "Node 'file:Engine.UnitTests/TestTestPlans/whiletest.TapPlan' has no edges (orphan)",
    "Node 'file:Engine/Cli/ExitCodes.cs' has no edges (orphan)",
    "Node 'file:Engine/IStartupInfo.cs' has no edges (orphan)",
    "Node 'file:Engine/IValidatingObject.cs' has no edges (orphan)",
    "Node 'file:Engine/IVisaFunctionLoader.cs' has no edges (orphan)",
    "Node 'file:Engine/IVisaProvider.cs' has no edges (orphan)",
    "Node 'file:Engine/Invokable/IInvokable.cs' has no edges (orphan)",
    "Node 'file:Engine/Invokable/ISkippableInvokable.cs' has no edges (orphan)",
    "Node 'file:Engine/LoadStatus.cs' has no edges (orphan)",
    "Node 'file:Engine/Properties/AssemblyInfo.cs' has no edges (orphan)",
    "Node 'file:Engine/Tap.Engine.csproj.vspscc' has no edges (orphan)",
    "Node 'file:Engine/Tap.snk' has no edges (orphan)",
    "Node 'file:Installer/Assets/LogoSide.bmp' has no edges (orphan)",
    "Node 'file:Installer/Assets/LogoTop.bmp' has no edges (orphan)",
    "Node 'file:Installer/Assets/Newtonsoft.Json.dll' has no edges (orphan)",
    "Node 'file:LinuxInstall/README' has no edges (orphan)",
    "Node 'file:LinuxInstall/package/Debian/control.in' has no edges (orphan)",
    "Node 'file:LinuxInstall/package/Debian/create-deb' has no edges (orphan)",
    "Node 'file:LinuxInstall/package/Debian/postinst.in' has no edges (orphan)",
    "Node 'file:nuget/OpenTAP.nuspec' has no edges (orphan)",
    "Node 'file:Engine/Verdict.cs' has no edges (orphan)",
    "Node 'file:Package.UnitTests/FilePackageRepoTest.cs' has no edges (orphan)",
    "Node 'file:Package.UnitTests/Packages/DependencyTest.dll' has no edges (orphan)",
    "Node 'file:Package.UnitTests/Packages/SetAsmInfoTest.dll' has no edges (orphan)",
    "Node 'file:Package.UnitTests/Properties/AssemblyInfo.cs' has no edges (orphan)",
    "Node 'file:Package/libgit2-b7bad55.source' has no edges (orphan)",
    "Node 'file:Package/PackageActions/PackageExitCodes.cs' has no edges (orphan)",
    "Node 'file:Package/Repositories/FileRepositoryCache.cs' has no edges (orphan)",
    "Node 'file:Package/Repositories/IPackageDownloadProgress.cs' has no edges (orphan)",
    "Node 'file:Package/Repositories/IQueryPrereleases.cs' has no edges (orphan)",
    "Node 'file:sdk/Examples/.HiddenFolder/Empty.txt' has no edges (orphan)",
    "Node 'file:sdk/Examples/.OpenTapIgnore' has no edges (orphan)",
    "Node 'file:sdk/Examples/Directory.Build.props' has no edges (orphan)",
    "Node 'file:sdk/Examples/ExamplePlugin/Properties/AssemblyInfo.cs' has no edges (orphan)",
    "Node 'file:sdk/OpenTap.Sdk.MSBuild/Properties/AssemblyInfo.cs' has no edges (orphan)",
    "Node 'file:sdk/OpenTap.Sdk.New/Properties/AssemblyInfo.cs' has no edges (orphan)",
    "Node 'file:sdk/Examples/TestPlanExecution/BuildTestPlan.Api/Properties/AssemblyInfo.cs' has no edges (orphan)",
    "Node 'file:sdk/Examples/TestPlanExecution/RunTestPlan.Api/Properties/AssemblyInfo.cs' has no edges (orphan)",
    "Node 'file:tap/Properties/AssemblyInfo.cs' has no edges (orphan)",
    "Node 'file:tap/Properties/AssemblyInfo.cs.Template' has no edges (orphan)",
    "Node 'file:tests/planWithLoadErrors.TapPlan' has no edges (orphan)"
  ],
  "stats": {
    "totalNodes": 3764,
    "totalEdges": 5679,
    "totalLayers": 9,
    "tourSteps": 14,
    "nodeTypes": {
      "service": 6,
      "pipeline": 4,
      "step": 34,
      "document": 69,
      "config": 95,
      "file": 679,
      "function": 1928,
      "class": 949
    },
    "edgeTypes": {
      "contains": 3340,
      "depends_on": 101,
      "inherits": 22,
      "related": 169,
      "documents": 6,
      "configures": 62,
      "exports": 1858,
      "calls": 91,
      "imports": 2,
      "tested_by": 17,
      "implements": 8,
      "deploys": 3
    }
  }
}